[
  {
    "path": "C:\\acmattos\\dev\\tools\\Python\\ia4devs\\module_05\\05_hackaton\\data\\sample\\aws_01.jpg",
    "boxes": [
      {
        "class": 53,
        "name": "Dynamo DB",
        "confidence": 0.9204151034355164,
        "coordinates": [
          467.8974304199219,
          361.7432861328125,
          522.8095703125,
          417.3059997558594
        ]
      },
      {
        "class": 102,
        "name": "Lambda",
        "confidence": 0.9174681901931763,
        "coordinates": [
          251.92820739746094,
          507.17401123046875,
          309.6674499511719,
          565.8317260742188
        ]
      },
      {
        "class": 141,
        "name": "SNS",
        "confidence": 0.8996211886405945,
        "coordinates": [
          565.1925659179688,
          32.88013458251953,
          620.8842163085938,
          90.52928161621094
        ]
      },
      {
        "class": 102,
        "name": "Lambda",
        "confidence": 0.8945895433425903,
        "coordinates": [
          354.1806335449219,
          133.94659423828125,
          408.27093505859375,
          189.5813751220703
        ]
      },
      {
        "class": 102,
        "name": "Lambda",
        "confidence": 0.8921459317207336,
        "coordinates": [
          467.19537353515625,
          33.135963439941406,
          522.2283935546875,
          89.16947937011719
        ]
      },
      {
        "class": 28,
        "name": "Cloud Watch",
        "confidence": 0.8822931051254272,
        "coordinates": [
          158.0777130126953,
          296.6115417480469,
          215.36399841308594,
          353.390869140625
        ]
      },
      {
        "class": 102,
        "name": "Lambda",
        "confidence": 0.8806982040405273,
        "coordinates": [
          564.9984741210938,
          361.0599060058594,
          621.881103515625,
          418.9096374511719
        ]
      },
      {
        "class": 141,
        "name": "SNS",
        "confidence": 0.8714537620544434,
        "coordinates": [
          353.0746154785156,
          507.3914489746094,
          410.5398864746094,
          565.4880981445312
        ]
      },
      {
        "class": 102,
        "name": "Lambda",
        "confidence": 0.8608909845352173,
        "coordinates": [
          354.6252746582031,
          295.8193664550781,
          410.92449951171875,
          354.0862731933594
        ]
      },
      {
        "class": 137,
        "name": "S3",
        "confidence": 0.8341330289840698,
        "coordinates": [
          254.85031127929688,
          133.70498657226562,
          312.458984375,
          190.93736267089844
        ]
      },
      {
        "class": 171,
        "name": "Users",
        "confidence": 0.8144621253013611,
        "coordinates": [
          561.0350952148438,
          508.9899597167969,
          609.2462768554688,
          560.5130615234375
        ]
      },
      {
        "class": 171,
        "name": "Users",
        "confidence": 0.7668482065200806,
        "coordinates": [
          672.0454711914062,
          163.90782165527344,
          717.977294921875,
          211.8400115966797
        ]
      },
      {
        "class": 28,
        "name": "Cloud Watch",
        "confidence": 0.766154944896698,
        "coordinates": [
          157.14483642578125,
          133.5327911376953,
          214.73667907714844,
          191.05145263671875
        ]
      },
      {
        "class": 28,
        "name": "Cloud Watch",
        "confidence": 0.7021474838256836,
        "coordinates": [
          661.4690551757812,
          360.8598937988281,
          719.2005615234375,
          418.27734375
        ]
      }
    ]
  }
]